maxwebhook
